darbiadev_manageorders/__init__.py
darbiadev_manageorders/lib/__init__.py
darbiadev_manageorders/lib/manage_orders.py
darbiadev_manageorders-0.2.0.dist-info/LICENSE
darbiadev_manageorders-0.2.0.dist-info/WHEEL
darbiadev_manageorders-0.2.0.dist-info/METADATA
darbiadev_manageorders-0.2.0.dist-info/RECORD
